docutranslate/__init__.py
docutranslate/app.py
docutranslate/cli.py
docutranslate/translater.py
docutranslate/agents/__init__.py
docutranslate/agents/agent.py
docutranslate/agents/markdown_agent.py
docutranslate/cacher/__init__.py
docutranslate/cacher/document_cacher.py
docutranslate/converter/__init__.py
docutranslate/converter/converter.py
docutranslate/converter/converter_docling.py
docutranslate/converter/converter_mineru.py
docutranslate/global_values/__init__.py
docutranslate/global_values/conditional_import.py
docutranslate/logger/__init__.py
docutranslate/logger/logger.py
docutranslate/static/DocuTranslate.ico
docutranslate/static/__init__.py
docutranslate/static/autoRender.js
docutranslate/static/index.html
docutranslate/static/katex.css
docutranslate/static/katex.js
docutranslate/static/mermaid.js
docutranslate/static/pico.css
docutranslate/template/__init__.py
docutranslate/template/markdown.html
docutranslate/utils/__init__.py
docutranslate/utils/docling_utils.py
docutranslate/utils/markdown_splitter.py
docutranslate/utils/markdown_utils.py
docutranslate/utils/resource_utils.py
docutranslate-0.2.41.dist-info/licenses/LICENSE
docutranslate-0.2.41.dist-info/METADATA
docutranslate-0.2.41.dist-info/WHEEL
docutranslate-0.2.41.dist-info/entry_points.txt
docutranslate-0.2.41.dist-info/top_level.txt
docutranslate-0.2.41.dist-info/RECORD
