Metadata-Version: 2.4
Name: docutranslate
Version: 0.2.41
Summary: 文件翻译工具
Requires-Python: >=3.10
License-File: LICENSE
Requires-Dist: httpx>=0.28.1
Requires-Dist: markdown2>=2.5.3
Requires-Dist: fastapi[standard]>=0.115.12
Provides-Extra: docling
Requires-Dist: opencv-python>=4.11.0.86; extra == "docling"
Requires-Dist: docling>=2.40.0; extra == "docling"
Dynamic: license-file
